emlabpkg/__init__.py
emlabpkg/gdspy_layouts/__init__.py
emlabpkg/gdspy_layouts/resonator_meanders.py
emlabpkg/instrument_drivers/BlueFors_LD400_API_Driver.py
emlabpkg/instrument_drivers/NF_ZM2376_Driver.py
emlabpkg/instrument_drivers/RCDAT_8000_90_Driver.py
emlabpkg/instrument_drivers/RS_RTC1002_Driver.py
emlabpkg/instrument_drivers/RS_ZNLE14_Driver.py
emlabpkg/instrument_drivers/__init__.py
emlabpkg/sweep/__init__.py
emlabpkg/sweep/db.py
emlabpkg/sweep/db_test.py
emlabpkg/sweep/plot.py
emlabpkg/sweep/sweep.py
emlabpkg/sweep/sweep_test.py
emlabpkg-4.34.dist-info/METADATA
emlabpkg-4.34.dist-info/WHEEL
emlabpkg-4.34.dist-info/top_level.txt
emlabpkg-4.34.dist-info/RECORD
