Metadata-Version: 2.1
Name: emlabpkg
Version: 4.34
Summary: Lab package for physics sweeps and LCR meter.
Home-page: https://github.com/Sushant1708/emlabpkg
Author: Sushant Padhye
Author-email: padhyesm@mail.uc.edu
Requires-Dist: qcodes
Requires-Dist: gdspy
